EQDBLinks/DBMySQL.py
EQDBLinks/DBRedist.py
EQDBLinks/DBSqlLite.py
EQDBLinks/DDLMKey.py
EQDBLinks/GetFromDB.py
EQDBLinks/__init__.py
EQStructure/MacdSKDJ.py
EQStructure/__init__.py
EQUseApi/ApiBase.py
EQUseApi/ApiFunc.py
EQUseApi/__init__.py
Functions/DirsFile.py
Functions/Formulae.py
Functions/LOG.py
Functions/PltImg.py
Functions/Structure.py
Functions/__init__.py
MainBase/MainBase.py
MainBase/__init__.py
THSFuncs/THSFuncs.py
THSFuncs/__init__.py
liwancai-1.0.0.dist-info/METADATA
liwancai-1.0.0.dist-info/WHEEL
liwancai-1.0.0.dist-info/top_level.txt
liwancai-1.0.0.dist-info/RECORD
