Metadata-Version: 2.1
Name: liwancai
Version: 1.0.0
Summary: liwancai的个人工具包
Home-page: https://github.com/liwancai/liwancai
Author: liwancai
Author-email: liwancai@example.com
Keywords: tools utilities data-analysis logging database
Platform: any
Classifier: Development Status :: 4 - Beta
Classifier: Intended Audience :: Developers
Classifier: License :: OSI Approved :: MIT License
Classifier: Programming Language :: Python :: 3
Classifier: Programming Language :: Python :: 3.6
Classifier: Programming Language :: Python :: 3.7
Classifier: Programming Language :: Python :: 3.8
Classifier: Programming Language :: Python :: 3.9
Classifier: Programming Language :: Python :: 3.10
Classifier: Programming Language :: Python :: 3.11
Classifier: Topic :: Software Development :: Libraries :: Python Modules
Classifier: Operating System :: OS Independent
Requires-Python: >=3.6
Requires-Dist: numpy>=1.16.0
Requires-Dist: pandas>=0.24.0
Requires-Dist: logbook>=1.5.3
Requires-Dist: requests>=2.22.0
Requires-Dist: tqdm>=4.32.0
Requires-Dist: prettytable>=0.7.2
Requires-Dist: toml>=0.10.0
Requires-Dist: pymysql>=1.0.0
Requires-Dist: sshtunnel>=0.4.0
